sparse_coo_matmul.sv
`timescale 1ns / 1ps

module sparse_coo_matmul(
    input logic rst,
    input wire clk,
    output logic [7:0][7:0][31:0] C   // Output matrix (8x8) in FP32
);

    // Hardcoded inputs for sparse matrix A
    logic [7:0][7:0] A_data ;  // Data values of A in FP8
    logic [7:0][31:0] A_row  ;  // Row indices of A
    logic [7:0][31:0] A_col;  // Column indices of A
    logic [31:0]      A_valid;  // Validity of the A entries

    // Hardcoded inputs for sparse matrix B
    logic [7:0][7:0] B_data ;  // Data values of B in FP8
    logic [7:0][31:0] B_row;  // Row indices of B
    logic [7:0][31:0] B_col;  // Column indices of B
    logic [31:0]      B_valid;  // Validity of the B entries

    integer i, j;

    // FP8 to real conversion function
    function automatic real fp8_to_real(input [7:0] fp8_value);
        logic sign;
        logic [3:0] exponent;
        logic [2:0] mantissa;
        real result;

        sign = fp8_value[7];
        exponent = fp8_value[6:3];
        mantissa = fp8_value[2:0];
        
        if (exponent == 4'b0000 && mantissa == 3'b000) begin
            result = 0.0;  // Zero
        end else begin
            result = (sign ? -1.0 : 1.0) * (1.0 + real'(mantissa) / 8.0) * (2.0 ** ($signed(exponent) - 7));
        end
        
        return result;
    endfunction

    // Initialize C to 0
    initial begin
        for (i = 0; i < 8; i = i + 1) begin
            for (j = 0; j < 8; j = j + 1) begin
                C[i][j] = 32'b0;  // Initialize C to 0 (FP32 format)
            end
        end
    end

    logic [7:0][7:0][31:0] c_mul = '0;  // Temporary matrix to accumulate results (FP32 format)
    logic [31:0] mul_result_bits;        // Declare this outside of always_ff

    always_ff @(posedge clk) begin
        if (rst) begin
        c_mul <= '0;  // Properly initialize C with 32-bit zero values
        A_data <= '0;  // Use non-blocking assignment to initialize A_data
        A_row  <= '0;  // Initialize A_row with 3-bit zeros
        A_col  <= '0;  // Initialize A_col with 3-bit zeros
        A_valid <= '0;  // Initialize A_valid with 1-bit zeros
        end else begin
            // Perform sparse matrix multiplication
            for (i = 0; i < 32; i = i + 1) begin
                if (A_valid[i]) begin
                    for (j = 0; j < 32; j = j + 1) begin
                        if (B_valid[j] && (A_col[i] == B_row[j])) begin
                            // Convert FP8 to real, multiply, and accumulate
                
                            real a_real, b_real, mul_result;
                            a_real = fp8_to_real(A_data[i]);
                        //    $display("world %f", a_real);

                            b_real = fp8_to_real(B_data[j]);
                            mul_result = a_real * b_real;

                            // $display("men %f", mul_result);

                            // Convert mul_result to bits, truncate to 32 bits, and accumulate
                            mul_result_bits <= $realtobits(mul_result)[63:32];  // Convert real to FP32 bits
                            $display("a_real * b_real = mul_result -- %f * %f = %f (%f)", a_real, b_real, mul_result, mul_result_bits);

                            c_mul[A_row[i]][B_col[j]] <= c_mul[A_row[i]][B_col[j]] + mul_result_bits;
                            //$display("hello %d",mul_result_bits);
                        end
                    end
                end
            end
        end
    end

    // Assign accumulated result to output C
    assign C = c_mul;

endmodule

tb_sparse_coo_matmul.sv
`timescale 1ns / 1ps

module tb_sparse_coo_matmul();

    // Testbench signals
    logic clk;
    logic rst;
    
    // 8x8 matrix of 32-bit elements (FP32 format)
    logic [31:0][7:0][7:0] C;  

    // Instantiate the Unit Under Test (UUT)
    sparse_coo_matmul uut (
        .rst(rst),
        .clk(clk),
        .C(C)
    );

    // Clock generation
    always begin
        #5 clk <= ~clk;  // 100 MHz clock
    end

    // Optional: Print matrix values if needed to avoid the unused signal warning
    task print_matrix;
        $display("Resulting Matrix C:");
        for (int i = 0; i < 8; i++) begin
            for (int j = 0; j < 8; j++) begin
                $display("C[%0d][%0d] = %d", i, j, C[i][j]);
            end
        end
    endtask

    // Testbench process
    initial begin
        // Initialize inputs
        $dumpfile("trace.vcd");
        $dumpvars();
        clk = 0;
        rst = 1;
        repeat(10) @(posedge clk);
        rst = 0;

        // Initialize the matrices A and B in the UUT using FP8 values
        // A matrix encoded in FP8 (E4M3)
        uut.A_data[0] = 8'b00111000; uut.A_row[0] = 0; uut.A_col[0] = 0; uut.A_valid[0] = 1;
        uut.A_data[1] = 8'b01000000; uut.A_row[1] = 0; uut.A_col[1] = 1; uut.A_valid[1] = 1;
        uut.A_data[2] = 8'b01001000; uut.A_row[2] = 0; uut.A_col[2] = 2; uut.A_valid[2] = 1;
        uut.A_data[3] = 8'b01010000; uut.A_row[3] = 1; uut.A_col[3] = 0; uut.A_valid[3] = 1;
        uut.A_data[4] = 8'b01011000; uut.A_row[4] = 1; uut.A_col[4] = 1; uut.A_valid[4] = 1;
        uut.A_data[5] = 8'b01100000; uut.A_row[5] = 1; uut.A_col[5] = 2; uut.A_valid[5] = 1;
        uut.A_data[6] = 8'b01101000; uut.A_row[6] = 2; uut.A_col[6] = 0; uut.A_valid[6] = 1;
        uut.A_data[7] = 8'b01110000; uut.A_row[7] = 2; uut.A_col[7] = 1; uut.A_valid[7] = 1;

        // Similar initialization for B matrix
        uut.B_data[0] = 8'b00111000; uut.B_row[0] = 0; uut.B_col[0] = 0; uut.B_valid[0] = 1;
        uut.B_data[1] = 8'b01000000; uut.B_row[1] = 1; uut.B_col[1] = 1; uut.B_valid[1] = 1;
        uut.B_data[2] = 8'b01001000; uut.B_row[2] = 2; uut.B_col[2] = 2; uut.B_valid[2] = 1;
        uut.B_data[3] = 8'b01010000; uut.B_row[3] = 3; uut.B_col[3] = 3; uut.B_valid[3] = 1;
        uut.B_data[4] = 8'b01011000; uut.B_row[4] = 1; uut.B_col[4] = 1; uut.B_valid[4] = 1;
        uut.B_data[5] = 8'b01100000; uut.B_row[5] = 1; uut.B_col[5] = 2; uut.B_valid[5] = 1;
        uut.B_data[6] = 8'b01101000; uut.B_row[6] = 2; uut.B_col[6] = 0; uut.B_valid[6] = 1;
        uut.B_data[7] = 8'b01110000; uut.B_row[7] = 2; uut.B_col[7] = 1; uut.B_valid[7] = 1;

        // Mark unused elements as invalid in both A and B matrices
        for (int i = 8; i < 32; i++) begin
            uut.A_valid[i] = 0;
            uut.B_valid[i] = 0;
        end
        
        
        // Simulation start
        // Run the simulation for 100 clock cycles
        repeat(10) @(posedge clk);
        
        // Optionally print matrix after simulation
        print_matrix();

        // Run for another 100 clock cycles
        repeat(100) @(posedge clk);

        // Finish the simulation
        $finish;
    end

endmodule

trace.vcd
$version Generated by VerilatedVcd $end
$timescale 1ps $end
 $scope module TOP $end
  $scope module tb_sparse_coo_matmul $end
   $var wire 1 v! clk $end
   $var wire 1 # rst $end
   $var wire 2048 /! C [2047:0] $end
   $scope module unnamedblk3 $end
    $var wire 32 $ i [31:0] $end
   $upscope $end
   $scope module uut $end
    $var wire 1 # rst $end
    $var wire 1 v! clk $end
    $var wire 2048 K C [2047:0] $end
    $var wire 64 8 A_data [63:0] $end
    $var wire 256 : A_row [255:0] $end
    $var wire 256 B A_col [255:0] $end
    $var wire 32 J A_valid [31:0] $end
    $var wire 64 % B_data [63:0] $end
    $var wire 256 ' B_row [255:0] $end
    $var wire 256 / B_col [255:0] $end
    $var wire 32 7 B_valid [31:0] $end
    $var wire 32 -! i [31:0] $end
    $var wire 32 .! j [31:0] $end
    $var wire 2048 /! c_mul [2047:0] $end
    $var wire 32 o! mul_result_bits [31:0] $end
    $scope module unnamedblk1 $end
     $var real 64 p! a_real $end
     $var real 64 r! b_real $end
     $var real 64 t! mul_result $end
    $upscope $end
   $upscope $end
  $upscope $end
 $upscope $end
$enddefinitions $end


#0
1#
b00000000000000000000000000000000 $
b0000000000000000000000000000000000000000000000000000000000000000 %
b0000000000000000000000000000000000000000000000000000000000000000000000000000000000000000000000000000000000000000000000000000000000000000000000000000000000000000000000000000000000000000000000000000000000000000000000000000000000000000000000000000000000000000 '
b0000000000000000000000000000000000000000000000000000000000000000000000000000000000000000000000000000000000000000000000000000000000000000000000000000000000000000000000000000000000000000000000000000000000000000000000000000000000000000000000000000000000000000 /
b00000000000000000000000000000000 7
b0000000000000000000000000000000000000000000000000000000000000000 8
b0000000000000000000000000000000000000000000000000000000000000000000000000000000000000000000000000000000000000000000000000000000000000000000000000000000000000000000000000000000000000000000000000000000000000000000000000000000000000000000000000000000000000000 :
b0000000000000000000000000000000000000000000000000000000000000000000000000000000000000000000000000000000000000000000000000000000000000000000000000000000000000000000000000000000000000000000000000000000000000000000000000000000000000000000000000000000000000000 B
b00000000000000000000000000000000 J
b00000000000000000000000000000000000000000000000000000000000000000000000000000000000000000000000000000000000000000000000000000000000000000000000000000000000000000000000000000000000000000000000000000000000000000000000000000000000000000000000000000000000000000000000000000000000000000000000000000000000000000000000000000000000000000000000000000000000000000000000000000000000000000000000000000000000000000000000000000000000000000000000000000000000000000000000000000000000000000000000000000000000000000000000000000000000000000000000000000000000000000000000000000000000000000000000000000000000000000000000000000000000000000000000000000000000000000000000000000000000000000000000000000000000000000000000000000000000000000000000000000000000000000000000000000000000000000000000000000000000000000000000000000000000000000000000000000000000000000000000000000000000000000000000000000000000000000000000000000000000000000000000000000000000000000000000000000000000000000000000000000000000000000000000000000000000000000000000000000000000000000000000000000000000000000000000000000000000000000000000000000000000000000000000000000000000000000000000000000000000000000000000000000000000000000000000000000000000000000000000000000000000000000000000000000000000000000000000000000000000000000000000000000000000000000000000000000000000000000000000000000000000000000000000000000000000000000000000000000000000000000000000000000000000000000000000000000000000000000000000000000000000000000000000000000000000000000000000000000000000000000000000000000000000000000000000000000000000000000000000000000000000000000000000000000000000000000000000000000000000000000000000000000000000000000000000000000000000000000000000000000000000000000000000000000000000000000000000000000000000000000000000000000000000000000000000000000000000000000000000000000000000000000000000000000000000000000000000000000000000000000000000000000000000000000000000000000000000000000000000000000000000000000000000000000000000000000000000000000000000000000000000000000000000000000000000000000000000000000000000000000000 K
b00000000000000000000000000001000 -!
b00000000000000000000000000001000 .!
b00000000000000000000000000000000000000000000000000000000000000000000000000000000000000000000000000000000000000000000000000000000000000000000000000000000000000000000000000000000000000000000000000000000000000000000000000000000000000000000000000000000000000000000000000000000000000000000000000000000000000000000000000000000000000000000000000000000000000000000000000000000000000000000000000000000000000000000000000000000000000000000000000000000000000000000000000000000000000000000000000000000000000000000000000000000000000000000000000000000000000000000000000000000000000000000000000000000000000000000000000000000000000000000000000000000000000000000000000000000000000000000000000000000000000000000000000000000000000000000000000000000000000000000000000000000000000000000000000000000000000000000000000000000000000000000000000000000000000000000000000000000000000000000000000000000000000000000000000000000000000000000000000000000000000000000000000000000000000000000000000000000000000000000000000000000000000000000000000000000000000000000000000000000000000000000000000000000000000000000000000000000000000000000000000000000000000000000000000000000000000000000000000000000000000000000000000000000000000000000000000000000000000000000000000000000000000000000000000000000000000000000000000000000000000000000000000000000000000000000000000000000000000000000000000000000000000000000000000000000000000000000000000000000000000000000000000000000000000000000000000000000000000000000000000000000000000000000000000000000000000000000000000000000000000000000000000000000000000000000000000000000000000000000000000000000000000000000000000000000000000000000000000000000000000000000000000000000000000000000000000000000000000000000000000000000000000000000000000000000000000000000000000000000000000000000000000000000000000000000000000000000000000000000000000000000000000000000000000000000000000000000000000000000000000000000000000000000000000000000000000000000000000000000000000000000000000000000000000000000000000000000000000000000000000000000000000000000000000000000000000000000 /!
b00000000000000000000000000000000 o!
r0 p!
r0 r!
r0 t!
0v!
#5000
1v!
#10000
0v!
#15000
1v!
#20000
0v!
#25000
1v!
#30000
0v!
#35000
1v!
#40000
0v!
#45000
1v!
#50000
0v!
#55000
1v!
#60000
0v!
#65000
1v!
#70000
0v!
#75000
1v!
#80000
0v!
#85000
1v!
#90000
0v!
#95000
0#
b00000000000000000000000000100000 $
b0111000001101000011000000101100001010000010010000100000000111000 %
b0000000000000000000000000000001000000000000000000000000000000010000000000000000000000000000000010000000000000000000000000000000100000000000000000000000000000011000000000000000000000000000000100000000000000000000000000000000100000000000000000000000000000000 '
b0000000000000000000000000000000100000000000000000000000000000000000000000000000000000000000000100000000000000000000000000000000100000000000000000000000000000011000000000000000000000000000000100000000000000000000000000000000100000000000000000000000000000000 /
b00000000000000000000000011111111 7
b0111000001101000011000000101100001010000010010000100000000111000 8
b0000000000000000000000000000001000000000000000000000000000000010000000000000000000000000000000010000000000000000000000000000000100000000000000000000000000000001000000000000000000000000000000000000000000000000000000000000000000000000000000000000000000000000 :
b0000000000000000000000000000000100000000000000000000000000000000000000000000000000000000000000100000000000000000000000000000000100000000000000000000000000000000000000000000000000000000000000100000000000000000000000000000000100000000000000000000000000000000 B
b00000000000000000000000011111111 J
b00000000000000000000000000100000 -!
b00000000000000000000000000100000 .!
b01000000101100000000000000000000 o!
r128 p!
r32 r!
r4096 t!
1v!
#100000
0v!
#105000
b00000000000000000000000000000000000000000000000000000000000000000000000000000000000000000000000000000000000000000000000000000000000000000000000000000000000000000000000000000000000000000000000000000000000000000000000000000000000000000000000000000000000000000000000000000000000000000000000000000000000000000000000000000000000000000000000000000000000000000000000000000000000000000000000000000000000000000000000000000000000000000000000000000000000000000000000000000000000000000000000000000000000000000000000000000000000000000000000000000000000000000000000000000000000000000000000000000000000000000000000000000000000000000000000000000000000000000000000000000000000000000000000000000000000000000000000000000000000000000000000000000000000000000000000000000000000000000000000000000000000000000000000000000000000000000000000000000000000000000000000000000000000000000000000000000000000000000000000000000000000000000000000000000000000000000000000000000000000000000000000000000000000000000000000000000000000000000000000000000000000000000000000000000000000000000000000000000000000000000000000000000000000000000000000000000000000000000000000000000000000000000000000000000000000000000000000000000000000000000000000000000000000000000000000000000000000000000000000000000000000000000000000000000000000000000000000000000000000000000000000000000000000000000000000000000000000000000000000000000000000000000000000000000000000000000000000000000000000000000000000001000000101100000000000000000000010000001011000000000000000000000100000010110000000000000000000000000000000000000000000000000000000000000000000000000000000000000000000000000000000000000000000000000000000000000000000000000000000000000000000000000000000000000100000010110000000000000000000001000000101100000000000000000000010000001011000000000000000000000000000000000000000000000000000000000000000000000000000000000000000000000000000000000000000000000000000000000000000000000000000000000000000000000000000000000000010000001011000000000000000000000100000010110000000000000000000001000000101100000000000000000000 K
b00000000000000000000000000000000000000000000000000000000000000000000000000000000000000000000000000000000000000000000000000000000000000000000000000000000000000000000000000000000000000000000000000000000000000000000000000000000000000000000000000000000000000000000000000000000000000000000000000000000000000000000000000000000000000000000000000000000000000000000000000000000000000000000000000000000000000000000000000000000000000000000000000000000000000000000000000000000000000000000000000000000000000000000000000000000000000000000000000000000000000000000000000000000000000000000000000000000000000000000000000000000000000000000000000000000000000000000000000000000000000000000000000000000000000000000000000000000000000000000000000000000000000000000000000000000000000000000000000000000000000000000000000000000000000000000000000000000000000000000000000000000000000000000000000000000000000000000000000000000000000000000000000000000000000000000000000000000000000000000000000000000000000000000000000000000000000000000000000000000000000000000000000000000000000000000000000000000000000000000000000000000000000000000000000000000000000000000000000000000000000000000000000000000000000000000000000000000000000000000000000000000000000000000000000000000000000000000000000000000000000000000000000000000000000000000000000000000000000000000000000000000000000000000000000000000000000000000000000000000000000000000000000000000000000000000000000000000000000000000000001000000101100000000000000000000010000001011000000000000000000000100000010110000000000000000000000000000000000000000000000000000000000000000000000000000000000000000000000000000000000000000000000000000000000000000000000000000000000000000000000000000000000000100000010110000000000000000000001000000101100000000000000000000010000001011000000000000000000000000000000000000000000000000000000000000000000000000000000000000000000000000000000000000000000000000000000000000000000000000000000000000000000000000000000000000010000001011000000000000000000000100000010110000000000000000000001000000101100000000000000000000 /!
1v!
#110000
0v!
#115000
b00000000000000000000000000000000000000000000000000000000000000000000000000000000000000000000000000000000000000000000000000000000000000000000000000000000000000000000000000000000000000000000000000000000000000000000000000000000000000000000000000000000000000000000000000000000000000000000000000000000000000000000000000000000000000000000000000000000000000000000000000000000000000000000000000000000000000000000000000000000000000000000000000000000000000000000000000000000000000000000000000000000000000000000000000000000000000000000000000000000000000000000000000000000000000000000000000000000000000000000000000000000000000000000000000000000000000000000000000000000000000000000000000000000000000000000000000000000000000000000000000000000000000000000000000000000000000000000000000000000000000000000000000000000000000000000000000000000000000000000000000000000000000000000000000000000000000000000000000000000000000000000000000000000000000000000000000000000000000000000000000000000000000000000000000000000000000000000000000000000000000000000000000000000000000000000000000000000000000000000000000000000000000000000000000000000000000000000000000000000000000000000000000000000000000000000000000000000000000000000000000000000000000000000000000000000000000000000000000000000000000000000000000000000000000000000000000000000000000000000000000000000000000000000000000000000000000000000000000000000000000000000000000000000000000000000000000000000000000000000000010000001011000000000000000000000100000010110000000000000000000001000000101100000000000000000000000000000000000000000000000000000000000000000000000000000000000000000000000000000000000000000000000000000000000000000000000000000000000000000000000000000000000001000000101100000000000000000000010000001011000000000000000000000100000010110000000000000000000000000000000000000000000000000000000000000000000000000000000000000000000000000000000000000000000000000000000000000000000000000000000000000000000000000000000000000100000010110000000000000000000001000000101100000000000000000000010000001011000000000000000000000 K
b00000000000000000000000000000000000000000000000000000000000000000000000000000000000000000000000000000000000000000000000000000000000000000000000000000000000000000000000000000000000000000000000000000000000000000000000000000000000000000000000000000000000000000000000000000000000000000000000000000000000000000000000000000000000000000000000000000000000000000000000000000000000000000000000000000000000000000000000000000000000000000000000000000000000000000000000000000000000000000000000000000000000000000000000000000000000000000000000000000000000000000000000000000000000000000000000000000000000000000000000000000000000000000000000000000000000000000000000000000000000000000000000000000000000000000000000000000000000000000000000000000000000000000000000000000000000000000000000000000000000000000000000000000000000000000000000000000000000000000000000000000000000000000000000000000000000000000000000000000000000000000000000000000000000000000000000000000000000000000000000000000000000000000000000000000000000000000000000000000000000000000000000000000000000000000000000000000000000000000000000000000000000000000000000000000000000000000000000000000000000000000000000000000000000000000000000000000000000000000000000000000000000000000000000000000000000000000000000000000000000000000000000000000000000000000000000000000000000000000000000000000000000000000000000000000000000000000000000000000000000000000000000000000000000000000000000000000000000000000000000010000001011000000000000000000000100000010110000000000000000000001000000101100000000000000000000000000000000000000000000000000000000000000000000000000000000000000000000000000000000000000000000000000000000000000000000000000000000000000000000000000000000000001000000101100000000000000000000010000001011000000000000000000000100000010110000000000000000000000000000000000000000000000000000000000000000000000000000000000000000000000000000000000000000000000000000000000000000000000000000000000000000000000000000000000000100000010110000000000000000000001000000101100000000000000000000010000001011000000000000000000000 /!
1v!
#120000
0v!
#125000
b00000000000000000000000000000000000000000000000000000000000000000000000000000000000000000000000000000000000000000000000000000000000000000000000000000000000000000000000000000000000000000000000000000000000000000000000000000000000000000000000000000000000000000000000000000000000000000000000000000000000000000000000000000000000000000000000000000000000000000000000000000000000000000000000000000000000000000000000000000000000000000000000000000000000000000000000000000000000000000000000000000000000000000000000000000000000000000000000000000000000000000000000000000000000000000000000000000000000000000000000000000000000000000000000000000000000000000000000000000000000000000000000000000000000000000000000000000000000000000000000000000000000000000000000000000000000000000000000000000000000000000000000000000000000000000000000000000000000000000000000000000000000000000000000000000000000000000000000000000000000000000000000000000000000000000000000000000000000000000000000000000000000000000000000000000000000000000000000000000000000000000000000000000000000000000000000000000000000000000000000000000000000000000000000000000000000000000000000000000000000000000000000000000000000000000000000000000000000000000000000000000000000000000000000000000000000000000000000000000000000000000000000000000000000000000000000000000000000000000000000000000000000000000000000000000000000000000000000000000000000000000000000000000000000000000000000000000000000000000000000011000010000100000000000000000000110000100001000000000000000000001100001000010000000000000000000000000000000000000000000000000000000000000000000000000000000000000000000000000000000000000000000000000000000000000000000000000000000000000000000000000000000000001100001000010000000000000000000011000010000100000000000000000000110000100001000000000000000000000000000000000000000000000000000000000000000000000000000000000000000000000000000000000000000000000000000000000000000000000000000000000000000000000000000000000000110000100001000000000000000000001100001000010000000000000000000011000010000100000000000000000000 K
b00000000000000000000000000000000000000000000000000000000000000000000000000000000000000000000000000000000000000000000000000000000000000000000000000000000000000000000000000000000000000000000000000000000000000000000000000000000000000000000000000000000000000000000000000000000000000000000000000000000000000000000000000000000000000000000000000000000000000000000000000000000000000000000000000000000000000000000000000000000000000000000000000000000000000000000000000000000000000000000000000000000000000000000000000000000000000000000000000000000000000000000000000000000000000000000000000000000000000000000000000000000000000000000000000000000000000000000000000000000000000000000000000000000000000000000000000000000000000000000000000000000000000000000000000000000000000000000000000000000000000000000000000000000000000000000000000000000000000000000000000000000000000000000000000000000000000000000000000000000000000000000000000000000000000000000000000000000000000000000000000000000000000000000000000000000000000000000000000000000000000000000000000000000000000000000000000000000000000000000000000000000000000000000000000000000000000000000000000000000000000000000000000000000000000000000000000000000000000000000000000000000000000000000000000000000000000000000000000000000000000000000000000000000000000000000000000000000000000000000000000000000000000000000000000000000000000000000000000000000000000000000000000000000000000000000000000000000000000000000000011000010000100000000000000000000110000100001000000000000000000001100001000010000000000000000000000000000000000000000000000000000000000000000000000000000000000000000000000000000000000000000000000000000000000000000000000000000000000000000000000000000000000001100001000010000000000000000000011000010000100000000000000000000110000100001000000000000000000000000000000000000000000000000000000000000000000000000000000000000000000000000000000000000000000000000000000000000000000000000000000000000000000000000000000000000110000100001000000000000000000001100001000010000000000000000000011000010000100000000000000000000 /!
1v!
#130000
0v!
#135000
b00000000000000000000000000000000000000000000000000000000000000000000000000000000000000000000000000000000000000000000000000000000000000000000000000000000000000000000000000000000000000000000000000000000000000000000000000000000000000000000000000000000000000000000000000000000000000000000000000000000000000000000000000000000000000000000000000000000000000000000000000000000000000000000000000000000000000000000000000000000000000000000000000000000000000000000000000000000000000000000000000000000000000000000000000000000000000000000000000000000000000000000000000000000000000000000000000000000000000000000000000000000000000000000000000000000000000000000000000000000000000000000000000000000000000000000000000000000000000000000000000000000000000000000000000000000000000000000000000000000000000000000000000000000000000000000000000000000000000000000000000000000000000000000000000000000000000000000000000000000000000000000000000000000000000000000000000000000000000000000000000000000000000000000000000000000000000000000000000000000000000000000000000000000000000000000000000000000000000000000000000000000000000000000000000000000000000000000000000000000000000000000000000000000000000000000000000000000000000000000000000000000000000000000000000000000000000000000000000000000000000000000000000000000000000000000000000000000000000000000000000000000000000000000000000000000000000000000000000000000000000000000000000000000000000000000000000000000000000000000000000000010110000000000000000000000000000101100000000000000000000000000001011000000000000000000000000000000000000000000000000000000000000000000000000000000000000000000000000000000000000000000000000000000000000000000000000000000000000000000000000000000000000000000001011000000000000000000000000000010110000000000000000000000000000101100000000000000000000000000000000000000000000000000000000000000000000000000000000000000000000000000000000000000000000000000000000000000000000000000000000000000000000000000000000000000000000101100000000000000000000000000001011000000000000000000000000000010110000000000000000000000 K
b00000000000000000000000000000000000000000000000000000000000000000000000000000000000000000000000000000000000000000000000000000000000000000000000000000000000000000000000000000000000000000000000000000000000000000000000000000000000000000000000000000000000000000000000000000000000000000000000000000000000000000000000000000000000000000000000000000000000000000000000000000000000000000000000000000000000000000000000000000000000000000000000000000000000000000000000000000000000000000000000000000000000000000000000000000000000000000000000000000000000000000000000000000000000000000000000000000000000000000000000000000000000000000000000000000000000000000000000000000000000000000000000000000000000000000000000000000000000000000000000000000000000000000000000000000000000000000000000000000000000000000000000000000000000000000000000000000000000000000000000000000000000000000000000000000000000000000000000000000000000000000000000000000000000000000000000000000000000000000000000000000000000000000000000000000000000000000000000000000000000000000000000000000000000000000000000000000000000000000000000000000000000000000000000000000000000000000000000000000000000000000000000000000000000000000000000000000000000000000000000000000000000000000000000000000000000000000000000000000000000000000000000000000000000000000000000000000000000000000000000000000000000000000000000000000000000000000000000000000000000000000000000000000000000000000000000000000000000000000000000000000010110000000000000000000000000000101100000000000000000000000000001011000000000000000000000000000000000000000000000000000000000000000000000000000000000000000000000000000000000000000000000000000000000000000000000000000000000000000000000000000000000000000000001011000000000000000000000000000010110000000000000000000000000000101100000000000000000000000000000000000000000000000000000000000000000000000000000000000000000000000000000000000000000000000000000000000000000000000000000000000000000000000000000000000000000000101100000000000000000000000000001011000000000000000000000000000010110000000000000000000000 /!
1v!
#140000
0v!
#145000
b00000000000000000000000000000000000000000000000000000000000000000000000000000000000000000000000000000000000000000000000000000000000000000000000000000000000000000000000000000000000000000000000000000000000000000000000000000000000000000000000000000000000000000000000000000000000000000000000000000000000000000000000000000000000000000000000000000000000000000000000000000000000000000000000000000000000000000000000000000000000000000000000000000000000000000000000000000000000000000000000000000000000000000000000000000000000000000000000000000000000000000000000000000000000000000000000000000000000000000000000000000000000000000000000000000000000000000000000000000000000000000000000000000000000000000000000000000000000000000000000000000000000000000000000000000000000000000000000000000000000000000000000000000000000000000000000000000000000000000000000000000000000000000000000000000000000000000000000000000000000000000000000000000000000000000000000000000000000000000000000000000000000000000000000000000000000000000000000000000000000000000000000000000000000000000000000000000000000000000000000000000000000000000000000000000000000000000000000000000000000000000000000000000000000000000000000000000000000000000000000000000000000000000000000000000000000000000000000000000000000000000000000000000000000000000000000000000000000000000000000000000000000000000000000000000000000000000000000000000000000000000000000000000000000000000000000000000000000000000000000001000011011100000000000000000000010000110111000000000000000000000100001101110000000000000000000000000000000000000000000000000000000000000000000000000000000000000000000000000000000000000000000000000000000000000000000000000000000000000000000000000000000000000100001101110000000000000000000001000011011100000000000000000000010000110111000000000000000000000000000000000000000000000000000000000000000000000000000000000000000000000000000000000000000000000000000000000000000000000000000000000000000000000000000000000000010000110111000000000000000000000100001101110000000000000000000001000011011100000000000000000000 K
b00000000000000000000000000000000000000000000000000000000000000000000000000000000000000000000000000000000000000000000000000000000000000000000000000000000000000000000000000000000000000000000000000000000000000000000000000000000000000000000000000000000000000000000000000000000000000000000000000000000000000000000000000000000000000000000000000000000000000000000000000000000000000000000000000000000000000000000000000000000000000000000000000000000000000000000000000000000000000000000000000000000000000000000000000000000000000000000000000000000000000000000000000000000000000000000000000000000000000000000000000000000000000000000000000000000000000000000000000000000000000000000000000000000000000000000000000000000000000000000000000000000000000000000000000000000000000000000000000000000000000000000000000000000000000000000000000000000000000000000000000000000000000000000000000000000000000000000000000000000000000000000000000000000000000000000000000000000000000000000000000000000000000000000000000000000000000000000000000000000000000000000000000000000000000000000000000000000000000000000000000000000000000000000000000000000000000000000000000000000000000000000000000000000000000000000000000000000000000000000000000000000000000000000000000000000000000000000000000000000000000000000000000000000000000000000000000000000000000000000000000000000000000000000000000000000000000000000000000000000000000000000000000000000000000000000000000000000000000000000000001000011011100000000000000000000010000110111000000000000000000000100001101110000000000000000000000000000000000000000000000000000000000000000000000000000000000000000000000000000000000000000000000000000000000000000000000000000000000000000000000000000000000000100001101110000000000000000000001000011011100000000000000000000010000110111000000000000000000000000000000000000000000000000000000000000000000000000000000000000000000000000000000000000000000000000000000000000000000000000000000000000000000000000000000000000010000110111000000000000000000000100001101110000000000000000000001000011011100000000000000000000 /!
1v!
#150000
0v!
#155000
b00000000000000000000000000000000000000000000000000000000000000000000000000000000000000000000000000000000000000000000000000000000000000000000000000000000000000000000000000000000000000000000000000000000000000000000000000000000000000000000000000000000000000000000000000000000000000000000000000000000000000000000000000000000000000000000000000000000000000000000000000000000000000000000000000000000000000000000000000000000000000000000000000000000000000000000000000000000000000000000000000000000000000000000000000000000000000000000000000000000000000000000000000000000000000000000000000000000000000000000000000000000000000000000000000000000000000000000000000000000000000000000000000000000000000000000000000000000000000000000000000000000000000000000000000000000000000000000000000000000000000000000000000000000000000000000000000000000000000000000000000000000000000000000000000000000000000000000000000000000000000000000000000000000000000000000000000000000000000000000000000000000000000000000000000000000000000000000000000000000000000000000000000000000000000000000000000000000000000000000000000000000000000000000000000000000000000000000000000000000000000000000000000000000000000000000000000000000000000000000000000000000000000000000000000000000000000000000000000000000000000000000000000000000000000000000000000000000000000000000000000000000000000000000000000000000000000000000000000000000000000000000000000000000000000000000000000000000000000000000000010000100001000000000000000000000100001000010000000000000000000001000010000100000000000000000000000000000000000000000000000000000000000000000000000000000000000000000000000000000000000000000000000000000000000000000000000000000000000000000000000000000000000001000010000100000000000000000000010000100001000000000000000000000100001000010000000000000000000000000000000000000000000000000000000000000000000000000000000000000000000000000000000000000000000000000000000000000000000000000000000000000000000000000000000000000100001000010000000000000000000001000010000100000000000000000000010000100001000000000000000000000 K
b00000000000000000000000000000000000000000000000000000000000000000000000000000000000000000000000000000000000000000000000000000000000000000000000000000000000000000000000000000000000000000000000000000000000000000000000000000000000000000000000000000000000000000000000000000000000000000000000000000000000000000000000000000000000000000000000000000000000000000000000000000000000000000000000000000000000000000000000000000000000000000000000000000000000000000000000000000000000000000000000000000000000000000000000000000000000000000000000000000000000000000000000000000000000000000000000000000000000000000000000000000000000000000000000000000000000000000000000000000000000000000000000000000000000000000000000000000000000000000000000000000000000000000000000000000000000000000000000000000000000000000000000000000000000000000000000000000000000000000000000000000000000000000000000000000000000000000000000000000000000000000000000000000000000000000000000000000000000000000000000000000000000000000000000000000000000000000000000000000000000000000000000000000000000000000000000000000000000000000000000000000000000000000000000000000000000000000000000000000000000000000000000000000000000000000000000000000000000000000000000000000000000000000000000000000000000000000000000000000000000000000000000000000000000000000000000000000000000000000000000000000000000000000000000000000000000000000000000000000000000000000000000000000000000000000000000000000000000000000000000010000100001000000000000000000000100001000010000000000000000000001000010000100000000000000000000000000000000000000000000000000000000000000000000000000000000000000000000000000000000000000000000000000000000000000000000000000000000000000000000000000000000000001000010000100000000000000000000010000100001000000000000000000000100001000010000000000000000000000000000000000000000000000000000000000000000000000000000000000000000000000000000000000000000000000000000000000000000000000000000000000000000000000000000000000000100001000010000000000000000000001000010000100000000000000000000010000100001000000000000000000000 /!
1v!
#160000
0v!
